[
	{
		"b_img" : "https://images.unsplash.com/photo-1522069169874-c58ec4b76be5?ixlib=rb-1.2.1&auto=format&fit=crop&w=1556&q=80"
	},
	{
		"b_img" : "https://images.unsplash.com/photo-1560942485-b2a11cc13456?ixlib=rb-1.2.1&ixid=eyJhcHBfaWQiOjEyMDd9&auto=format&fit=crop&w=1576&q=80"
	},
	{
		"b_img" : "https://images.unsplash.com/photo-1560292290-616d4329614b?ixlib=rb-1.2.1&ixid=eyJhcHBfaWQiOjEyMDd9&auto=format&fit=crop&w=1562&q=80"
	},
	{
		"b_img" : "https://images.unsplash.com/photo-1516683037151-9a17603a8dc7?ixlib=rb-1.2.1&ixid=eyJhcHBfaWQiOjEyMDd9&auto=format&fit=crop&w=1544&q=80"
	},
	{
		"b_img" : "https://images.unsplash.com/photo-1518399681705-1c1a55e5e883?ixlib=rb-1.2.1&ixid=eyJhcHBfaWQiOjEyMDd9&auto=format&fit=crop&w=1482&q=80"
	},
	{
		"b_img" : "https://images.unsplash.com/photo-1495594059084-33752639b9c3?ixlib=rb-1.2.1&auto=format&fit=crop&w=1600&q=80"
	},
	{
		"b_img" : "https://images.unsplash.com/photo-1480109866847-0b432ceb666a?ixlib=rb-1.2.1&ixid=eyJhcHBfaWQiOjEyMDd9&auto=format&fit=crop&w=1575&q=80"
	}
]